[
  {
    "message": "aaaaaaaaaaaaaaaa",
    "type": "warning",
    "isActive": true,
    "dismissible": true,
    "link": "",
    "linkText": "",
    "expiresAt": null,
    "id": "announcement_1751142282483_zdpuyqd5f",
    "createdAt": "2025-06-28T20:24:42.483Z"
  },
  {
    "message": "امروز",
    "type": "promotion",
    "isActive": false,
    "dismissible": true,
    "link": "",
    "linkText": "",
    "expiresAt": null,
    "id": "announcement_1751141431243_xeh4el26v",
    "createdAt": "2025-06-28T20:10:31.243Z",
    "updatedAt": "2025-06-28T20:22:54.374Z"
  }
]